icw_kv_quant.py
icw_kv_quant-0.1.0.dist-info/licenses/LICENSE
icw_kv_quant-0.1.0.dist-info/METADATA
icw_kv_quant-0.1.0.dist-info/WHEEL
icw_kv_quant-0.1.0.dist-info/top_level.txt
icw_kv_quant-0.1.0.dist-info/RECORD
