Metadata-Version: 2.4
Name: icw-kv-quant
Version: 0.1.0
Summary: ICW Key-Value Quantization library
Author-email: Alex Sheff <alex42ff@gmail.com>
License: MIT
Requires-Python: >=3.8
License-File: LICENSE
Dynamic: license-file
